{
    "scenario":  "queue-saturation",
    "runStamp":  "2026-06-11_051256",
    "gitSha":  "unknown",
    "dockerHost":  "tcp://192.168.100.70:2375",
    "rate":  300,
    "warmupMin":  2,
    "steadyMin":  5,
    "jfr":  false,
    "startupMs":  12268,
    "k6ExitCode":  0,
    "runValid":  true,
    "scenarioJvmOpts":  "-javaagent:/otel/opentelemetry-javaagent.jar -Dotel.javaagent.extensions=/otel/platform-tracing-otel-extension-agent.jar -Dotel.exporter.otlp.endpoint=http://toxiproxy:4318 -Dotel.exporter.otlp.protocol=http/protobuf -Dplatform.tracing.sampling.ratio=1.0 -Dotel.bsp.max.queue.size=32 -Dplatform.tracing.queue.overflow-policy=DROP_OLDEST",
    "cpusets":  {
                    "sut":  null,
                    "k6":  null,
                    "collector":  null
                },
    "analysis":  {
                     "run":  {
                                 "cpuSeconds":  51.89,
                                 "cpuUtilization":  0.1763,
                                 "rssAvgMb":  616.3,
                                 "rssMaxMb":  623.3,
                                 "rssSlopeMbPerMin":  4.437,
                                 "steadySamples":  58,
                                 "p99Ms":  2.88
                             },
                     "baseline":  {
                                      "cpuSeconds":  49.41,
                                      "cpuUtilization":  0.0832,
                                      "rssAvgMb":  509.7,
                                      "rssMaxMb":  514.1,
                                      "rssSlopeMbPerMin":  0.984,
                                      "steadySamples":  116,
                                      "p99Ms":  1.14
                                  },
                     "delta":  {
                                   "cpuPct":  111.9,
                                   "rssPct":  20.91,
                                   "p99Ms":  1.74
                               }
                 }
}
